pyrsistent_as_rpds/__init__.py
pyrsistent_as_rpds/auto.py
pyrsistent_as_rpds/pure.py
pyrsistent_as_rpds/py.typed
pyrsistent_as_rpds_py-2.1.0.dist-info/AUTHORS.md
pyrsistent_as_rpds_py-2.1.0.dist-info/LICENSE
pyrsistent_as_rpds_py-2.1.0.dist-info/METADATA
pyrsistent_as_rpds_py-2.1.0.dist-info/WHEEL
pyrsistent_as_rpds_py-2.1.0.dist-info/top_level.txt
pyrsistent_as_rpds_py-2.1.0.dist-info/RECORD
