Metadata-Version: 2.1
Name: pyrsistent-as-rpds-py
Version: 2.1.0
Summary: Adapter which implements a subset of rpds-py using pyrsistent. Mostly meant for PyPy.
Author-email: Eduard Christian Dumitrescu <eduard.c.dumitrescu@gmail.com>
Maintainer-email: Eduard Christian Dumitrescu <eduard.c.dumitrescu@gmail.com>
License: MIT
Project-URL: Homepage, https://github.com/e-c-d/pyrsistent-as-rpds-py/
Classifier: Programming Language :: Python :: 3
License-File: LICENSE
License-File: AUTHORS.md
Provides-Extra: pure
Requires-Dist: pyrsistent ; extra == 'pure'
Provides-Extra: pyrsistent
Requires-Dist: pyrsistent ; extra == 'pyrsistent'
Provides-Extra: rpds-py
Requires-Dist: rpds-py ; extra == 'rpds-py'
